mongo_client/__init__.py
mongo_client/client.py
mongo_utils/__init__.py
mongo_utils/mongo_orm.py
mongo_utils/serializers.py
mongopyorm-0.3.5.dist-info/METADATA
mongopyorm-0.3.5.dist-info/WHEEL
mongopyorm-0.3.5.dist-info/top_level.txt
mongopyorm-0.3.5.dist-info/RECORD
