Metadata-Version: 2.1
Name: mongopyorm
Version: 0.3.5
Summary: A lightweight Python Object-Relational Mapper (ORM)-like implementation for MongoDB
Author: Ambar Rizvi
Author-email: <brannstrom9911@gmail.com>
Keywords: mongodb,ORM,database,MongoDB ORM,Django,Django ORM
Classifier: Development Status :: 3 - Alpha
Classifier: Intended Audience :: Developers
Classifier: Programming Language :: Python :: 3
Classifier: License :: OSI Approved :: MIT License
Classifier: Operating System :: Unix
Classifier: Operating System :: MacOS :: MacOS X
Classifier: Operating System :: Microsoft :: Windows
Requires-Python: >=3.6
Requires-Dist: pymongo>=4.10.1
